{
    "name": "knetquery",
    "targetType": "executable",
    "description": "A Knowledge Network/Graph Command Line Query tool.",
    "copyright": "Copyright © 2015, Per Nordlöw",
    "buildRequirements": ["allowWarnings"],
    "importPaths": [ ".." ],
    "sourceFiles": [ "../dbg.d", "../msgpack.d", "../predicates.d",

                     "../knet/languages.d",
                     "../knet/roles.d",
                     "../knet/origins.d",
                     "../knet/thematics.d",

                     "../knet/base.d",
                     "../knet/tests.d",
                     "../knet/iteration.d",
                     "../knet/inference.d",
                     "../knet/persistence.d",
                     "../knet/io.d",

                     "../knet/decodings.d",
                     "../knet/relations.d",
                     "../knet/senses.d",
                     "../knet/lemmas.d",

                     "../knet/readers/cn5.d",
                     "../knet/readers/nell.d",
                     "../knet/readers/wordnet.d",
                     "../knet/readers/moby.d",
                     "../knet/readers/synlex.d",
                     "../knet/readers/folklex.d",
                     "../knet/readers/swesaurus.d",

                     "../knet/lectures/all.d",
                     "../wordnet.d",
                     "../grammars.d", "../stemming.d", "../ixes.d",
                     "../assert_ex.d", "../range_ex.d", "../algorithm_ex.d", "../traits_ex.d", "../sort_ex.d", "../mmfile_ex.d", "../skip_ex.d",
                     "../bylines.d",
                     "../rational.d", "../combinations.d", "../permutations.d", "../arsd/dom.d", "../arsd/characterencodings.d",
                     "../backtrace/backtrace.d" ]
}
